discord_bind/__init__.py
discord_bind/admin.py
discord_bind/app_settings.py
discord_bind/apps.py
discord_bind/conf.py
discord_bind/models.py
discord_bind/urls.py
discord_bind/views.py
discord_bind/__pycache__/__init__.cpython-35.pyc
discord_bind/__pycache__/app_settings.cpython-35.pyc
discord_bind/migrations/0001_initial.py
discord_bind/migrations/__init__.py
discord_bind/tests/__init__.py
discord_bind/tests/test_callback_view.py
discord_bind/tests/test_index_view.py
discord_bind/tests/test_models.py
discord_bind/tests/test_views.py
django_discord_bind-0.2.0.dist-info/DESCRIPTION.rst
django_discord_bind-0.2.0.dist-info/METADATA
django_discord_bind-0.2.0.dist-info/RECORD
django_discord_bind-0.2.0.dist-info/WHEEL
django_discord_bind-0.2.0.dist-info/metadata.json
django_discord_bind-0.2.0.dist-info/top_level.txt
